llama_index/llms/nvidia/__init__.py
llama_index/llms/nvidia/base.py
llama_index/llms/nvidia/utils.py
llama_index_llms_nvidia-0.4.4.dist-info/METADATA
llama_index_llms_nvidia-0.4.4.dist-info/WHEEL
llama_index_llms_nvidia-0.4.4.dist-info/licenses/LICENSE
llama_index_llms_nvidia-0.4.4.dist-info/RECORD
