Metadata-Version: 2.4
Name: llama-index-llms-nvidia
Version: 0.4.4
Summary: llama-index llms nvidia api catalog integration
Author-email: Chris Alexiuk <calexiuk@nvidia.com>
License-Expression: MIT
License-File: LICENSE
Requires-Python: <4.0,>=3.9
Requires-Dist: llama-index-llms-openai-like<0.6,>=0.5.0
